README.md
setup.py
cs_bitcoin_model/__init__.py
cs_bitcoin_model/cs_bitcoin_model.py
cs_bitcoin_model.egg-info/PKG-INFO
cs_bitcoin_model.egg-info/SOURCES.txt
cs_bitcoin_model.egg-info/dependency_links.txt
cs_bitcoin_model.egg-info/requires.txt
cs_bitcoin_model.egg-info/top_level.txt
cs_bitcoin_model/cert/__init__.py
cs_bitcoin_model/cert/nginx.cryptosloth.io.crt
cs_bitcoin_model/cert/nginx.cryptosloth.io.key
cs_bitcoin_model/config/__init__.py
cs_bitcoin_model/config/production.config
cs_bitcoin_model/config/test.config
cs_bitcoin_model/crypto/__init__.py
cs_bitcoin_model/crypto/aggregate/__init__.py
cs_bitcoin_model/crypto/aggregate/btc_prediction/__init__.py
cs_bitcoin_model/crypto/aggregate/btc_prediction/binance_client.py
cs_bitcoin_model/crypto/aggregate/btc_prediction/worker_predict_btc_price.py
cs_bitcoin_model/crypto/aggregate/crawling/__init__.py
cs_bitcoin_model/crypto/aggregate/crawling/web_crawling.py
cs_bitcoin_model/crypto/aggregate/cryoto_quant/__init__.py
cs_bitcoin_model/crypto/aggregate/cryoto_quant/classify_indicator_ex_netflow.py
cs_bitcoin_model/crypto/aggregate/cryoto_quant/classify_indicator_leverage_ratio.py
cs_bitcoin_model/crypto/aggregate/cryoto_quant/classify_indicator_liquidation.py
cs_bitcoin_model/crypto/aggregate/cryoto_quant/classify_indicator_mpi.py
cs_bitcoin_model/crypto/aggregate/cryoto_quant/classify_indicator_mvrv.py
cs_bitcoin_model/crypto/aggregate/cryoto_quant/classify_indicator_nupl.py
cs_bitcoin_model/crypto/aggregate/cryoto_quant/classify_indicator_nvt_golden.py
cs_bitcoin_model/crypto/aggregate/cryoto_quant/classify_indicator_puell.py
cs_bitcoin_model/crypto/aggregate/cryoto_quant/classify_indicator_ratio_usd.py
cs_bitcoin_model/crypto/aggregate/cryoto_quant/classify_indicator_sopr.py
cs_bitcoin_model/crypto/aggregate/cryoto_quant/classify_indicator_sopr_holders.py
cs_bitcoin_model/crypto/aggregate/cryoto_quant/classify_indicator_utxo.py
cs_bitcoin_model/crypto/aggregate/cryoto_quant/crypto_quant_api.py
cs_bitcoin_model/crypto/aggregate/defi/__init__.py
cs_bitcoin_model/crypto/aggregate/defi/staking.py
cs_bitcoin_model/crypto/aggregate/exchain_client/__init__.py
