Metadata-Version: 2.1
Name: cs-bitcoin-model
Version: 0.0.5
Summary: predict bitcoin based on data everyday
Home-page: https://github.com/phamhung3589/cs_bitcoin_model.git
Author: hungph
Author-email: phamhung3589@gmail.com
License: MIT Licence
Keywords: cs_bitcoin_model,cs,bitcoin model
Platform: any
Requires-Python: >=3.6
